int.py
streams.py
uint.py
uintlib-2.0.0.dist-info/licenses/LICENSE
uintlib-2.0.0.dist-info/METADATA
uintlib-2.0.0.dist-info/WHEEL
uintlib-2.0.0.dist-info/top_level.txt
uintlib-2.0.0.dist-info/RECORD
