Metadata-Version: 2.4
Name: uintlib
Version: 2.0.0
Summary: A Python package to easily use uints/ints in Python. 
Author: rraptor06
License: MIT
Keywords: python
Classifier: Programming Language :: Python :: 3
Classifier: License :: OSI Approved :: MIT License
Classifier: Operating System :: OS Independent
Requires-Python: >=3.6
License-File: LICENSE
Dynamic: license-file
